batch_gcd/__init__.py
batch_gcd/py.typed
batch_gcd-0.0.3.dist-info/METADATA
batch_gcd-0.0.3.dist-info/WHEEL
batch_gcd-0.0.3.dist-info/top_level.txt
batch_gcd-0.0.3.dist-info/RECORD
