Metadata-Version: 2.1
Name: batch-gcd
Version: 0.0.3
Summary: Pure Python implementation of DJB's Batch GCD algorithm
Home-page: https://github.com/fionn/batch-gcd
Author: Fionn Fitzmaurice
License: UNKNOWN
Project-URL: Source Code, https://github.com/fionn/batch-gcd
Project-URL: Changelog, https://github.com/fionn/batch-gcd/tags
Project-URL: Documentation, https://github.com/fionn/batch-gcd/blob/master/README.md
Project-URL: Bug Tracker, https://github.com/fionn/batch-gcd/issues
Project-URL: PyPI, https://pypi.org/project/batch-gcd/
Project-URL: Download, https://github.com/fionn/batch-gcd/archive/refs/heads/master.zip
Keywords: gcd
Platform: UNKNOWN
Classifier: Programming Language :: Python :: 3
Classifier: Development Status :: 4 - Beta
Classifier: Intended Audience :: Developers
Classifier: Topic :: Security :: Cryptography
Classifier: Topic :: Scientific/Engineering :: Mathematics
Classifier: Typing :: Typed
Requires-Python: >=3.9
Provides-Extra: dev
Requires-Dist: pylint ; extra == 'dev'
Requires-Dist: mypy ; extra == 'dev'
Requires-Dist: coverage ; extra == 'dev'
